Metadata-Version: 1.0
Name: weebhooks
Version: 1.0.0
Summary: weebhooks - A lib for interacting with Discord webhooks.
Home-page: https://github.com/bananaboy21/weebhooks
Author: dat banana boi
Author-email: kang.eric.hi@gmail.com
License: MIT
Platform: UNKNOWN
